Workbook

Sheet CASH FLOW
A1: MONTH/FORECAST | B1: CASH INFLOW | C1: CASH OUTFLOW | D1: NET CASH FLOW | E1: OPENING BALANCE | F1: CLOSING BALANCE | G1: OBSERVATION
A2: APRIL | B2: 50000 | C2: 40000 | D2: =B2-C2 -> 10000 | E2: 100000 | F2: =E2+D2 -> 110000
A3: MAY | B3: 60000 | C3: 45000 | D3: =B3-C3 -> 15000 | E3: =F2 -> 110000 | F3: =E3+D3 -> 125000
A4: JUNE | B4: 55000 | C4: 50000 | D4: =B4-C4 -> 5000 | E4: =F3 -> 125000 | F4: =E4+D4 -> 130000 | G4: LOW BUFFER MONTH
A5: JULY | B5: 70000 | C5: 52000 | D5: =B5-C5 -> 18000 | E5: =F4 -> 130000 | F5: =E5+D5 -> 148000
A6: AUGUST | B6: 65000 | C6: 40000 | D6: =B6-C6 -> 25000 | E6: =F5 -> 148000 | F6: =E6+D6 -> 173000
A7: SEPTEMBER | B7: 52000 | C7: 45000 | D7: =B7-C7 -> 7000 | E7: =F6 -> 173000 | F7: =E7+D7 -> 180000
A8: OCTOBER | B8: 42000 | C8: 48000 | D8: =B8-C8 -> -6000 | E8: =F7 -> 180000 | F8: =E8+D8 -> 174000 | G8: NEGATIVE CASH FLOW DUE TO HIGHER EXPENSES
A9: NOVEMBER | B9: 68000 | C9: 52000 | D9: =B9-C9 -> 16000 | E9: =F8 -> 174000 | F9: =E9+D9 -> 190000
A10: DECEMBER | B10: 57000 | C10: 40000 | D10: =B10-C10 -> 17000 | E10: =F9 -> 190000 | F10: =E10+D10 -> 207000
A11: JANUARY | B11: 72000 | C11: 45000 | D11: =B11-C11 -> 27000 | E11: =F10 -> 207000 | F11: =E11+D11 -> 234000 | G11: STRONG LIQUIDITY MONTH
A12: FEBRUARY | B12: 59000 | C12: 50000 | D12: =B12-C12 -> 9000 | E12: =F11 -> 234000 | F12: =E12+D12 -> 243000 | G12: MODERATE CASH SURPLUS MAINTAINED
A13: MARCH | B13: 61000 | C13: 52000 | D13: =B13-C13 -> 9000 | E13: =F12 -> 243000 | F13: =E13+D13 -> 252000 | G13: MODERATE CASH SURPLUS MAINTAINED
A14: APRIL(FORECAST) | B14: =B13*(1+ASSUMPTIONS!B1) -> 65880 | C14: =C13*(1+ASSUMPTIONS!B2) -> 54600 | D14: =B14-C14 -> 11280 | E14: =F13 -> 252000 | F14: =E14+D14 -> 263280
A15: MAY(FORECAST) | B15: =B14*(1+ASSUMPTIONS!B1) -> 71150.4 | C15: =C14*(1+ASSUMPTIONS!B2) -> 57330 | D15: =B15-C15 -> 13820.4 | E15: =F14 -> 263280 | F15: =E15+D15 -> 277100.4
A16: JUNE(FORECAST) | B16: =B15*(1+ASSUMPTIONS!B1) -> 76842.432 | C16: =C15*(1+ASSUMPTIONS!B2) -> 60196.5 | D16: =B16-C16 -> 16645.932 | E16: =F15 -> 277100.4 | F16: =E16+D16 -> 293746.33
A17: JULY(FORECAST) | B17: =B16*(1+ASSUMPTIONS!B1) -> 82989.827 | C17: =C16*(1+ASSUMPTIONS!B2) -> 63206.325 | D17: =B17-C17 -> 19783.502 | E17: =F16 -> 293746.33 | F17: =E17+D17 -> 313529.83
A18: AUGUST(FORECAST) | B18: =B17*(1+ASSUMPTIONS!B1) -> 89629.013 | C18: =C17*(1+ASSUMPTIONS!B2) -> 66366.641 | D18: =B18-C18 -> 23262.371 | E18: =F17 -> 313529.83 | F18: =E18+D18 -> 336792.2
A19: SEPTEMBER(FORECAST) | B19: =B18*(1+ASSUMPTIONS!B1) -> 96799.334 | C19: =C18*(1+ASSUMPTIONS!B2) -> 69684.973 | D19: =B19-C19 -> 27114.36 | E19: =F18 -> 336792.2 | F19: =E19+D19 -> 363906.57

Sheet ASSUMPTIONS
A1: GROWTH IN INFLOW | B1: 0.08
A2: INCREASE IN OUTFLOW | B2: 0.05
A3: BEST CASE SCENARIO
A4: BEST CASE INFLOW GROWTH | B4: 0.12
A5: BEST CASE OUTFLOW GROWTH | B5: 0.03
A6: WORST CASE SCENARIO
A7: WORST CASE INFLOW GROWTH | B7: 0.03
A8: WORST CASE OUTFLOW GROWTH | B8: 0.1

Sheet BEST CASE SCENARIO
A1: MONTH/FORECAST | B1: CASH INFLOW | C1: CASH OUTFLOW | D1: NET CASH FLOW | E1: OPENING BALANCE | F1: CLOSING BALANCE
A2: APRIL(FORECAST) | B2: ='CASH FLOW'!B13*(1+ASSUMPTIONS!B4) -> 68320 | C2: ='CASH FLOW'!C13*(1+ASSUMPTIONS!B5) -> 53560 | D2: =B2-C2 -> 14760 | E2: 252000 | F2: =D2+E2 -> 266760
A3: MAY(FORECAST) | B3: =B2*(1+ASSUMPTIONS!B4) -> 76518.4 | C3: =C2*(1+ASSUMPTIONS!B5) -> 55166.8 | D3: =B3-C3 -> 21351.6 | E3: =F2 -> 266760 | F3: =D3+E3 -> 288111.6
A4: JUNE(FORECAST) | B4: =B3*(1+ASSUMPTIONS!B4) -> 85700.608 | C4: =C3*(1+ASSUMPTIONS!B5) -> 56821.804 | D4: =B4-C4 -> 28878.804 | E4: =F3 -> 288111.6 | F4: =D4+E4 -> 316990.4
A5: JULY(FORECAST) | B5: =B4*(1+ASSUMPTIONS!B4) -> 95984.681 | C5: =C4*(1+ASSUMPTIONS!B5) -> 58526.458 | D5: =B5-C5 -> 37458.223 | E5: =F4 -> 316990.4 | F5: =D5+E5 -> 354448.63
A6: AUGUST(FORECAST) | B6: =B5*(1+ASSUMPTIONS!B4) -> 107502.84 | C6: =C5*(1+ASSUMPTIONS!B5) -> 60282.252 | D6: =B6-C6 -> 47220.591 | E6: =F5 -> 354448.63 | F6: =D6+E6 -> 401669.22
A7: SEPTEMBER(FORECAST) | B7: =B6*(1+ASSUMPTIONS!B4) -> 120403.18 | C7: =C6*(1+ASSUMPTIONS!B5) -> 62090.719 | D7: =B7-C7 -> 58312.464 | E7: =F6 -> 401669.22 | F7: =D7+E7 -> 459981.68

Sheet WORST CASE SCENARIO
A1: MONTH/FORECAST | B1: CASH INFLOW | C1: CASH OUTFLOW | D1: NET CASH FLOW | E1: OPENING BALANCE | F1: CLOSING BALANCE | G1: OBSERVATION
A2: APRIL(FORECAST) | B2: ='CASH FLOW'!B13*(1+ASSUMPTIONS!B7) -> 62830 | C2: ='CASH FLOW'!C13*(1+ASSUMPTIONS!B8) -> 57200 | D2: =B2-C2 -> 5630 | E2: 252000 | F2: =D2+E2 -> 257630
A3: MAY(FORECAST) | B3: =B2*(1+ASSUMPTIONS!B7) -> 64714.9 | C3: =C2*(1+ASSUMPTIONS!B8) -> 62920 | D3: =B3-C3 -> 1794.9 | E3: =F2 -> 257630 | F3: =D3+E3 -> 259424.9
A4: JUNE(FORECAST) | B4: =B3*(1+ASSUMPTIONS!B7) -> 66656.347 | C4: =C3*(1+ASSUMPTIONS!B8) -> 69212 | D4: =B4-C4 -> -2555.653 | E4: =F3 -> 259424.9 | F4: =D4+E4 -> 256869.25
A5: JULY(FORECAST) | B5: =B4*(1+ASSUMPTIONS!B7) -> 68656.037 | C5: =C4*(1+ASSUMPTIONS!B8) -> 76133.2 | D5: =B5-C5 -> -7477.1626 | E5: =F4 -> 256869.25 | F5: =D5+E5 -> 249392.08
A6: AUGUST(FORECAST) | B6: =B5*(1+ASSUMPTIONS!B7) -> 70715.719 | C6: =C5*(1+ASSUMPTIONS!B8) -> 83746.52 | D6: =B6-C6 -> -13030.801 | E6: =F5 -> 249392.08 | F6: =D6+E6 -> 236361.28
A7: SEPTEMBER(FORECAST) | B7: =B6*(1+ASSUMPTIONS!B7) -> 72837.19 | C7: =C6*(1+ASSUMPTIONS!B8) -> 92121.172 | D7: =B7-C7 -> -19283.982 | E7: =F6 -> 236361.28 | F7: =D7+E7 -> 217077.3 | G7: CASH STRESS BEGINS HERE- MANAGEMENT ACTION REQUIRED

Sheet EXECUTIVE SUMMARY
A1: PURPOSE OF ANALYSIS
A2: This cash flow forecasting model is prepared to analyze monthly liquidity position and identify potential cash surplus or deficit under different scenorios (Base,Best, and worst case)
A4: KEY FINDINGS
A5: BASE CASE
A6: 1. Monthly cash flows remains positive for most periods
A7: 2. October shows negative net cash flow due to higher outflows
A8: 3. January reflects the strongest liquidity position
A9: 4. June shows thin cash buffer and needs monitoring
A11: RISK ANALYSIS
A12: 1. Cash deficit risk arises if inflows slow and expenses increase
A13: 2. worst case scenerio indicates possible cash stress in september month
A14: 3. Sustained negative cash flow may require external funding or cost control
... A37: BELOW 20,000 - CRITICAL
